LICENSE.txt
MANIFEST.in
README.md
setup.py
Markdown_Table_Formatter/Markdown_Table_Formatter.py
Markdown_Table_Formatter/__init__.py
markdown_table_formatter.egg-info/PKG-INFO
markdown_table_formatter.egg-info/SOURCES.txt
markdown_table_formatter.egg-info/dependency_links.txt
markdown_table_formatter.egg-info/entry_points.txt
markdown_table_formatter.egg-info/top_level.txt