Metadata-Version: 2.1
Name: markdown-table-formatter
Version: 0.1.0
Summary: A tool to format Markdown tables by aligning columns.
Home-page: https://github.com/pyTabib/Markdown_Table_Formatter
Author: Tabib
Author-email: pytabib@gmail.com
Classifier: Programming Language :: Python :: 3
Classifier: License :: OSI Approved :: MIT License
Classifier: Operating System :: OS Independent
Requires-Python: >=3.6
License-File: LICENSE.txt
